forgeo/rigs/__init__.py
forgeo/rigs/_version.py
forgeo/rigs/gmconverter.py
forgeo/rigs/rigs.pyd
forgeo/rigs/tetcube.py
forgeo/rigs/trirect.py
forgeo/rigs/utils.py
lib/librobust_implicit_networks.a
forgeo_rigs-0.2.dist-info/METADATA
forgeo_rigs-0.2.dist-info/WHEEL
forgeo_rigs-0.2.dist-info/licenses/LICENSE
forgeo_rigs-0.2.dist-info/RECORD
