Metadata-Version: 2.2
Name: forgeo-rigs
Version: 0.2
Summary: A python library for geological implicit modeling.
Author-Email: Simon LOPEZ <s.lopez@brgm.fr>
Requires-Dist: numpy
Provides-Extra: test
Requires-Dist: vtkwriters; extra == "test"
Requires-Dist: matplotlib; extra == "test"
Requires-Dist: forgeo-gmlib>=0.6.1; extra == "test"
